protein_inference/__init__.py
protein_inference/main.py
protein_inference/network_grapher.py
protein_inference/problem_network.py
protein_inference/protein_inference_runner.py
protein_inference/table_maker.py
protein_inference/benchmarking/__init__.py
protein_inference/benchmarking/benchmark_percolator_inference.py
protein_inference/benchmarking/benchmarking.py
protein_inference/benchmarking/entrapment_benchmark.py
protein_inference/inference/__init__.py
protein_inference/inference/false_discovery_rate_calculator.py
protein_inference/inference/protein_merger.py
protein_inference/inference/scorers.py
protein_inference/inference/uniqueness_tagger.py
protein_inference/processing/__init__.py
protein_inference/processing/processed_psms.py
protein_inference/processing/psms_network_generator.py
protein_inference/processing/psms_network_splitter.py
protein_inference/processing/psms_preprocessor.py
protein_inference/reprisal/__init__.py
protein_inference/reprisal/greedy_algorithm.py
tests/__init__.py
protein_inference-0.2.2.dist-info/LICENSE.txt
protein_inference-0.2.2.dist-info/METADATA
protein_inference-0.2.2.dist-info/WHEEL
protein_inference-0.2.2.dist-info/top_level.txt
protein_inference-0.2.2.dist-info/RECORD
